{
  "schema": 1,
  "updated_at": "2026-07-21T08:52:08+00:00",
  "items": [
    {
      "date": "2026-07-21",
      "generated_at": "2026-07-21T08:52:08+00:00",
      "assets": {
        "BTC": {
          "price_usd": 66202.93187500001,
          "change_24h": 0.03474137675025677,
          "market_cap_usd": 1328180087183.549
        },
        "ETH": {
          "price_usd": 1939.2780775,
          "change_24h": 0.04312312702284877,
          "market_cap_usd": 234041468125.76648
        },
        "HYPE": {
          "price_usd": 62.99,
          "change_24h": 0.038518931872473516,
          "market_cap_usd": 14012317363.572145
        },
        "SOL": {
          "price_usd": 78.364702,
          "change_24h": 0.030523511294386983,
          "market_cap_usd": 45676834233.03403
        },
        "BNB": {
          "price_usd": 577.2799799999999,
          "change_24h": 0.02229700752290651,
          "market_cap_usd": 76888970538.14989
        },
        "XRP": {
          "price_usd": 1.1328794899999999,
          "change_24h": 0.042636438354971086,
          "market_cap_usd": 70820068641.10718
        },
        "DOGE": {
          "price_usd": 0.07353738,
          "change_24h": 0.025724206638986703,
          "market_cap_usd": 11413075330.871395
        }
      },
      "derivatives": {
        "BTC": {
          "funding_annualized_median": 0.101453283,
          "quarterly_basis_annualized": 0.04473915970674141,
          "dvol": 36.37,
          "put_call_open_interest_ratio": 0.45372770598169554
        },
        "ETH": {
          "funding_annualized_median": 0.08261227500000001,
          "quarterly_basis_annualized": 0.018086061459897548,
          "dvol": 50.12,
          "put_call_open_interest_ratio": 0.5086941069368501
        }
      },
      "sectors": {
        "RWA": 0.005223760091661478,
        "Layer 1": 0.02611835750842185,
        "DeFi": 0.03136265235630871,
        "Meme": 0.016392934802466706
      },
      "dat": {
        "BTC": {
          "total_holdings": 1285045.0097809657,
          "companies": {
            "MSTR.US": 843775.0,
            "XXI.US": 43514.0,
            "3350.T": 43000.0,
            "MARA.US": 35303.0,
            "CEPO.US": 30021.0,
            "GLXY.US": 25723.0,
            "BLSH.US": 23300.0,
            "ASST.US": 19000.0
          }
        },
        "ETH": {
          "total_holdings": 7786998.905876,
          "companies": {
            "BMNR.US": 5777468.0,
            "SBET.US": 868699.0,
            "ETHM.US": 496712.0,
            "BTBT.US": 158461.75,
            "COIN.US": 150193.0,
            "BTCS.US": 70787.0,
            "FRMM.US": 69802.0,
            "GLXY.US": 61137.0
          }
        }
      },
      "btc_thesis": {
        "btc_to_gold_market_value_ratio": 0.04618023651927969,
        "gold_price_as_of": "2026-07-21T08:42:01+00:00",
        "stablecoin_supply_usd": 308358845738.1259,
        "stablecoin_supply_30d_change": -0.018709642767534396,
        "stablecoin_as_of": "2026-07-21T08:52:08+00:00",
        "public_company_share_of_supply": 0.06406334007711519,
        "public_company_as_of": "2026-07-21T08:52:05+00:00",
        "hashrate_vs_90d_high": 0.8196321707455707,
        "hashrate_as_of": "2026-07-20T00:00:00+00:00",
        "us_10y_real_yield_pct": 2.31,
        "us_10y_real_yield_as_of": "2026-07-17",
        "us_federal_debt_to_gdp_as_of": "2026-01-01",
        "quality_status": "degraded"
      },
      "quality_status": "degraded"
    }
  ]
}
